mutual_information/__init__.py
mutual_information/mf.py
mutual_information/mf_random.py
mutual_information/synergy_tree.py
mutual_information-0.0.5.dist-info/METADATA
mutual_information-0.0.5.dist-info/WHEEL
mutual_information-0.0.5.dist-info/namespace_packages.txt
mutual_information-0.0.5.dist-info/top_level.txt
mutual_information-0.0.5.dist-info/zip-safe
mutual_information-0.0.5.dist-info/RECORD
