Metadata-Version: 2.1
Name: mutual-information
Version: 0.0.5
Summary: UNKNOWN
Home-page: https://github.com/kingmanzhang/mutual-information
Author: Xingmin Aaron Zhang
Author-email: kingmanzhang@gmail.com
Maintainer: 
Maintainer-email: 
License: MIT
Platform: UNKNOWN
Classifier: Development Status :: 3 - Alpha
Classifier: Programming Language :: Python
Requires-Dist: networkx
Requires-Dist: numpy
Requires-Dist: pandas
Requires-Dist: treelib
